parasplit/Frag.py
parasplit/Pretreatment.py
parasplit/Read.py
parasplit/WriteAndControl.py
parasplit/__init__.py
parasplit/main.py
parasplit-1.1.2.dist-info/METADATA
parasplit-1.1.2.dist-info/WHEEL
parasplit-1.1.2.dist-info/entry_points.txt
parasplit-1.1.2.dist-info/top_level.txt
parasplit-1.1.2.dist-info/RECORD
