Metadata-Version: 2.1
Name: parasplit
Version: 1.1.2
Summary: An Hi-C tool for cutting sequences using specified enzymes
Author-email: Bertache Djenadi <samir.bertache.djenadi@gmail.com>
License: AGPLv3
Keywords: Hi-C,HiC,bioinformatics,cutsite
Requires-Dist: biopython ==1.83
